shopyo_dashboard/__init__.py
shopyo_dashboard/info.json
shopyo_dashboard/view.py
shopyo_dashboard/templates/shopyo_dashboard/index.html
shopyo_dashboard/templates/shopyo_dashboard/nav.html
shopyo_dashboard-1.4.0.dist-info/METADATA
shopyo_dashboard-1.4.0.dist-info/WHEEL
shopyo_dashboard-1.4.0.dist-info/top_level.txt
shopyo_dashboard-1.4.0.dist-info/RECORD
