Metadata-Version: 2.4
Name: shopyo_dashboard
Version: 1.4.0
Summary: Base module containing jinja macros and templates
Author-email: Abdur-Rahmaan Janhangeer <arj.python@gmail.com>
Project-URL: Homepage, https://github.com/shopyo/shopyo
Project-URL: Bug Tracker, https://github.com/shopyo/shopyo/issues
Keywords: shopyo
Classifier: Programming Language :: Python :: 3
Classifier: License :: OSI Approved :: BSD License
Classifier: Operating System :: OS Independent
Requires-Python: >=3.8
Requires-Dist: shopyo
Requires-Dist: shopyo_auth
Requires-Dist: shopyo_appadmin
